choices/__init__.py
choices/choices.py
choices/utils.py
choices.py-0.1.1.dist-info/LICENSE.txt
choices.py-0.1.1.dist-info/METADATA
choices.py-0.1.1.dist-info/RECORD
choices.py-0.1.1.dist-info/WHEEL
choices.py-0.1.1.dist-info/top_level.txt
